half_adder/half_adder.v
module half_adder(
    input  wire a,
    input  wire b,
    output wire cout,
    output wire sum
);
    
    and(cout, a, b);
    xor(sum, a, b);
endmodule

full_adder/full_adder.v
`include "../half_adder/half_adder.v"

module full_adder(
    input  wire a,
    input  wire b,
    input  wire cin,
    output wire cout,
    output wire sum
);
    
    wire c1, c2, s1;

    half_adder ha1(a, b, c1, s1);
    half_adder ha2(s1, cin, c2, sum);
    or (cout, c1, c2);
endmodule

full_adder/full_adder_tb.v
module full_adder_tb;
    reg a, b, cin;
    wire cout, sum;
    
    full_adder fa(a, b, cin, cout, sum);

    initial begin
        $dumpfile("full_adder_tb.vcd");
        $dumpvars(0, full_adder_tb);
        #50 a=1'b0; b=1'b0; cin=1'b0;
        #50 a=1'b0; b=1'b0; cin=1'b1;
        #50 a=1'b0; b=1'b1; cin=1'b0;
        #50 a=1'b0; b=1'b1; cin=1'b1;
        #50 a=1'b1; b=1'b0; cin=1'b0;
        #50 a=1'b1; b=1'b0; cin=1'b1;
        #50 a=1'b1; b=1'b1; cin=1'b0;
        #50 a=1'b1; b=1'b1; cin=1'b1;
        #50 $finish;
    end
endmodule

full_adder/full_adder_tb.vcd
$date
	Wed Feb 16 16:33:24 2022
$end
$version
	Icarus Verilog
$end
$timescale
	1s
$end
$scope module full_adder_tb $end
$var wire 1 ! sum $end
$var wire 1 " cout $end
$var reg 1 # a $end
$var reg 1 $ b $end
$var reg 1 % cin $end
$scope module fa $end
$var wire 1 # a $end
$var wire 1 $ b $end
$var wire 1 % cin $end
$var wire 1 " cout $end
$var wire 1 ! sum $end
$var wire 1 & s1 $end
$var wire 1 ' c2 $end
$var wire 1 ( c1 $end
$scope module ha1 $end
$var wire 1 # a $end
$var wire 1 $ b $end
$var wire 1 ( cout $end
$var wire 1 & sum $end
$upscope $end
$scope module ha2 $end
$var wire 1 & a $end
$var wire 1 % b $end
$var wire 1 ' cout $end
$var wire 1 ! sum $end
$upscope $end
$upscope $end
$upscope $end
$enddefinitions $end
#0
$dumpvars
x(
x'
x&
x%
x$
x#
x"
x!
$end
#50
0"
0'
0!
0(
0&
0%
0$
0#
#100
1!
1%
#150
1&
0%
1$
#200
1"
1'
0!
1%
#250
0"
0'
1!
0%
0$
1#
#300
1"
1'
0!
1%
#350
0'
1(
0&
0%
1$
#400
1!
1%
